Metadata-Version: 2.1
Name: fluentdctl
Version: 0.0.4
Summary: A CLI for Fluentd API
Home-page: UNKNOWN
Author: Max Anderson
Author-email: <cctpmax@gmail.com>
License: UNKNOWN
Project-URL: GitHub, https://github.com/MaxAnderson95/fluentdctl
Keywords: fluentd,cli
Platform: UNKNOWN
Classifier: Development Status :: 1 - Planning
Classifier: Intended Audience :: Developers
Classifier: Programming Language :: Python :: 3
Classifier: Operating System :: Unix
Classifier: Operating System :: MacOS :: MacOS X
Classifier: Operating System :: Microsoft :: Windows
License-File: LICENSE
